TSGroupAssigner/__init__.py
TSGroupAssigner/exceptions.py
TSGroupAssigner/group_assign.py
TSGroupAssigner-0.2.dist-info/LICENCE.md
TSGroupAssigner-0.2.dist-info/METADATA
TSGroupAssigner-0.2.dist-info/WHEEL
TSGroupAssigner-0.2.dist-info/top_level.txt
TSGroupAssigner-0.2.dist-info/RECORD
