Metadata-Version: 2.1
Name: TSGroupAssigner
Version: 0.2
Summary: date based TeamSpeak Group Assigner
Home-page: https://github.com/mightyBroccoli/TSGroupAssigner
Author: nico wellpott
Author-email: nico@magicbroccoli.de
License: GPLv3
Project-URL: Source, https://github.com/mightyBroccoli/TSGroupAssigner
Project-URL: Issue-Tracker, https://github.com/mightyBroccoli/TSGroupAssigner/issues
Keywords: automation TeamSpeak teamspeak ts3 ts3server ts
Platform: UNKNOWN
Classifier: Intended Audience :: System Administrators
Classifier: Natural Language :: English
Classifier: License :: OSI Approved :: GNU General Public License v3 (GPLv3)
Classifier: Operating System :: Unix
Classifier: Programming Language :: Python :: 3
Classifier: Programming Language :: Python :: 3.6
Classifier: Programming Language :: Python :: 3.7
Classifier: Programming Language :: Python :: 3.8
Classifier: Programming Language :: Python :: Implementation :: CPython
Classifier: Topic :: Communications
Classifier: Topic :: Internet
Requires-Python: >=3.6
Requires-Dist: ts3 (<2,>=1.0.11)
